fontastical/__init__.py
fontastical-1.1.0.dist-info/LICENSE
fontastical-1.1.0.dist-info/METADATA
fontastical-1.1.0.dist-info/WHEEL
fontastical-1.1.0.dist-info/top_level.txt
fontastical-1.1.0.dist-info/RECORD
