Metadata-Version: 2.1
Name: fontastical
Version: 1.1.0
Summary: Fancy fonts for your terminal!
Home-page: https://replit.com/@EpicCodeWizard/Fontastical
Author: EpicCodeWizard
Author-email: epiccodewizard@gmail.com
License: UNKNOWN
Platform: UNKNOWN
Classifier: Programming Language :: Python :: 3
Classifier: License :: OSI Approved :: MIT License
Classifier: Operating System :: OS Independent
Requires-Python: >=3.6
